anchormake/__init__.py
anchormake/ankermake.py
anchormake-0.1.0.dist-info/LICENSE
anchormake-0.1.0.dist-info/METADATA
anchormake-0.1.0.dist-info/WHEEL
anchormake-0.1.0.dist-info/top_level.txt
anchormake-0.1.0.dist-info/RECORD
